mcmendiburu_package/Inverse.py
mcmendiburu_package/__init__.py
mcmendiburu_package-0.1.0.dist-info/METADATA
mcmendiburu_package-0.1.0.dist-info/WHEEL
mcmendiburu_package-0.1.0.dist-info/top_level.txt
mcmendiburu_package-0.1.0.dist-info/RECORD
